python_unicorn-0.4.4.data/scripts/fn-delete
python_unicorn-0.4.4.data/scripts/fn-push
unicorn/__init__.py
unicorn/utils.py
unicorn/client/__init__.py
unicorn/client/admin_client.py
unicorn/client/api_client.py
unicorn/client/utils.py
python_unicorn-0.4.4.dist-info/LICENSE
python_unicorn-0.4.4.dist-info/METADATA
python_unicorn-0.4.4.dist-info/WHEEL
python_unicorn-0.4.4.dist-info/top_level.txt
python_unicorn-0.4.4.dist-info/RECORD
